setup.py
alex_mess_server.egg-info/PKG-INFO
alex_mess_server.egg-info/SOURCES.txt
alex_mess_server.egg-info/dependency_links.txt
alex_mess_server.egg-info/requires.txt
alex_mess_server.egg-info/top_level.txt
server/__init__.py
server/launcher.py
server/server.py
server/common/__init__.py
server/common/decos.py
server/common/descryptors.py
server/common/errors.py
server/common/metaclasses.py
server/common/utils.py
server/common/variables.py
server/project_logs/__init__.py
server/project_logs/configs/__init__.py
server/project_logs/configs/client_log_config.py
server/project_logs/configs/server_log_config.py
server/project_logs/logs/__init__.py
server/server/__init__.py
server/server/add_user.py
server/server/config_window.py
server/server/core.py
server/server/database.py
server/server/main_window.py
server/server/remove_user.py
server/server/stat_window.py
server/unit_tests/__init__.py
server/unit_tests/test_client.py
server/unit_tests/test_server.py
server/unit_tests/test_utils.py